ok_redirects/__init__.py
ok_redirects/admin.py
ok_redirects/apps.py
ok_redirects/conf.py
ok_redirects/constants.py
ok_redirects/fields.py
ok_redirects/middleware.py
ok_redirects/models.py
ok_redirects/recievers.py
ok_redirects/responses.py
ok_redirects/services.py
ok_redirects/utils.py
ok_redirects/migrations/0001_initial.py
ok_redirects/migrations/0002_redirect_is_active.py
ok_redirects/migrations/0003_auto_20200908_1334.py
ok_redirects/migrations/0004_auto_20201218_1122.py
ok_redirects/migrations/0005_auto_20210112_0814.py
ok_redirects/migrations/0006_auto_20220414_1213.py
ok_redirects/migrations/__init__.py
django_ok_redirects-0.4.0.dist-info/LICENSE
django_ok_redirects-0.4.0.dist-info/METADATA
django_ok_redirects-0.4.0.dist-info/WHEEL
django_ok_redirects-0.4.0.dist-info/top_level.txt
django_ok_redirects-0.4.0.dist-info/RECORD
