Metadata-Version: 2.1
Name: django-ok-redirects
Version: 0.4.0
Summary: Simple Redirects App, which is particularly useful in the cases where you want to update some existing URLs without compromising your Website SEO.
Home-page: https://github.com/LowerDeez/ok-redirects
Author: Oleg Kleschunov
Author-email: igorkleschunov@gmail.com
License: MIT
Keywords: python,redirects,redirects-models,django
Classifier: Development Status :: 4 - Beta
Classifier: Environment :: Web Environment
Classifier: Intended Audience :: Developers
Classifier: License :: OSI Approved :: MIT License
Classifier: Operating System :: OS Independent
Classifier: Programming Language :: Python
Classifier: Programming Language :: Python :: 3.6
Classifier: Programming Language :: Python :: 3.7
Classifier: Programming Language :: Python :: 3.8
Classifier: Programming Language :: Python :: 3.9
Classifier: Programming Language :: Python :: 3.10
Classifier: Programming Language :: Python :: 3.11
Classifier: Programming Language :: Python :: 3.12
Classifier: Framework :: Django
Classifier: Framework :: Django :: 2.2
Classifier: Framework :: Django :: 3.1
Classifier: Framework :: Django :: 3.2
Classifier: Framework :: Django :: 4.2
Classifier: Framework :: Django :: 5.0
License-File: LICENSE
Requires-Dist: django >=3.2
Requires-Dist: six
Requires-Dist: mock
